clipkeeper/__init__.py
clipkeeper/run.py
clipkeeper/cli/__init__.py
clipkeeper/cli/commands.py
clipkeeper/core/__init__.py
clipkeeper/core/clipboard.py
clipkeeper/core/manager.py
clipkeeper/utils/__init__.py
clipkeeper/utils/logger.py
clipkeeper/web/__init__.py
clipkeeper/web/server.py
clipkeeper/web/static/css/styles.css
clipkeeper/web/static/js/main.js
clipkeeper/web/templates/index.html
clipkeeper-0.1.5.dist-info/LICENSE
clipkeeper-0.1.5.dist-info/METADATA
clipkeeper-0.1.5.dist-info/WHEEL
clipkeeper-0.1.5.dist-info/entry_points.txt
clipkeeper-0.1.5.dist-info/top_level.txt
clipkeeper-0.1.5.dist-info/RECORD
