Metadata-Version: 2.1
Name: clipkeeper
Version: 0.1.5
Summary: A Windows-based clipboard history manager
Home-page: https://github.com/wittiness/clipkeeper
Author: wittiness
License: MIT
Classifier: License :: OSI Approved :: MIT License
Classifier: Programming Language :: Python :: 3
Classifier: Programming Language :: Python :: 3.8
Classifier: Programming Language :: Python :: 3.9
Classifier: Programming Language :: Python :: 3.10
Requires-Python: >=3.8
License-File: LICENSE
Requires-Dist: Flask<3.0.0,>=2.0.0
Requires-Dist: Flask-SocketIO<6.0.0,>=5.0.0
Requires-Dist: click<9.0.0,>=8.0.0
Requires-Dist: pathlib<2.0.0,>=1.0.1
Requires-Dist: Werkzeug<3.0.0,>=2.0.0
Requires-Dist: Jinja2<4.0.0,>=3.0.0
Requires-Dist: itsdangerous<3.0.0,>=2.0.0
Requires-Dist: python-dateutil<3.0.0,>=2.8.0
Requires-Dist: rich>=12.0.0
Requires-Dist: colorama<1.0.0,>=0.4.4
Requires-Dist: pyperclip>=1.8.2
Requires-Dist: pywin32>=305
Requires-Dist: pillow==11.0.0
Provides-Extra: dev
Requires-Dist: pytest<8.0.0,>=7.0.0; extra == "dev"
Requires-Dist: pytest-cov<5.0.0,>=4.0.0; extra == "dev"
Requires-Dist: pytest-mock<4.0.0,>=3.10.0; extra == "dev"
Requires-Dist: black<24.0.0,>=23.0.0; extra == "dev"
Requires-Dist: flake8<7.0.0,>=6.0.0; extra == "dev"
Requires-Dist: mypy<2.0.0,>=1.0.0; extra == "dev"
Requires-Dist: isort<6.0.0,>=5.0.0; extra == "dev"
Requires-Dist: Sphinx<7.0.0,>=6.0.0; extra == "dev"
Requires-Dist: sphinx-rtd-theme<2.0.0,>=1.2.0; extra == "dev"
Requires-Dist: build<1.0.0,>=0.10.0; extra == "dev"
Requires-Dist: twine<5.0.0,>=4.0.0; extra == "dev"
Provides-Extra: windows
Requires-Dist: pywin32>=305; extra == "windows"
